djangopasswordlessknox
