Metadata-Version: 2.1
Name: djangopasswordlessknox
Version: 1.4.0
Summary: Passwordless auth for Django Rest Framework Knox Token Authentication.
Home-page: https://github.com/lijoev/django-rest-framework-passwordless-knox
Author: Lijo
Author-email: lijoev@gmail.com
License: MIT
Platform: UNKNOWN
Classifier: License :: OSI Approved :: MIT License
Classifier: Programming Language :: Python
Classifier: Programming Language :: Python :: 3
Classifier: Programming Language :: Python :: 3.6
Classifier: Programming Language :: Python :: Implementation :: CPython
Classifier: Programming Language :: Python :: Implementation :: PyPy
Classifier: Development Status :: 5 - Production/Stable
Classifier: Environment :: Web Environment
Classifier: Framework :: Django
Classifier: Intended Audience :: Developers
Classifier: Operating System :: OS Independent
Classifier: Programming Language :: Python
Classifier: Topic :: Internet :: WWW/HTTP
Requires-Python: >=3
